xfeltor/__init__.py
xfeltor/feltordataarray.py
xfeltor/feltordataset.py
xfeltor/load.py
xfeltor/plotting.py
xfeltor-0.1.1.dist-info/licenses/LICENSE
xfeltor-0.1.1.dist-info/METADATA
xfeltor-0.1.1.dist-info/WHEEL
xfeltor-0.1.1.dist-info/top_level.txt
xfeltor-0.1.1.dist-info/RECORD
