Metadata-Version: 2.4
Name: xfeltor
Version: 0.1.1
Summary: Collect FELTOR simulation data into xarray
Author-email: Gregor Decristoforo <gregor.decristoforo@uit.no>, Matthias Wiesenberger <mattwi@fysik.dtu.dk>
License: MIT License
Project-URL: Source, https://github.com/feltor-dev/xFELTOR
Project-URL: Tracker, https://github.com/feltor-dev/xFELTOR/issues
Classifier: Intended Audience :: Science/Research
Classifier: Intended Audience :: Education
Classifier: Intended Audience :: Developers
Classifier: Natural Language :: English
Classifier: Operating System :: POSIX :: Linux
Classifier: Programming Language :: Python :: 3
Classifier: Topic :: Scientific/Engineering :: Visualization
Requires-Python: >=3.10
License-File: LICENSE
Requires-Dist: xarray>=2025.3.1
Requires-Dist: dask>=2025.3.0
Requires-Dist: natsort>=8.4.0
Requires-Dist: matplotlib>=3.10.1
Requires-Dist: animatplot>=0.4.3
Requires-Dist: netcdf4>=1.7.2
Requires-Dist: Pillow>=11.1.0
Provides-Extra: test
Requires-Dist: pytest; extra == "test"
Provides-Extra: lint
Requires-Dist: ruff; extra == "lint"
Provides-Extra: docs
Requires-Dist: sphinx>=5.3; extra == "docs"
Requires-Dist: sphinx_autodoc_typehints>=1.19; extra == "docs"
Requires-Dist: sphinx-book-theme>=0.4.0rc1; extra == "docs"
Requires-Dist: myst_parser; extra == "docs"
Dynamic: license-file
